pydicomimg/__init__.py
pydicomimg/pydicomimg.py
pydicomimg-0.0.7.dist-info/METADATA
pydicomimg-0.0.7.dist-info/WHEEL
pydicomimg-0.0.7.dist-info/top_level.txt
pydicomimg-0.0.7.dist-info/RECORD
